tsextract/__init__.py
tsextract/domain/__init__.py
tsextract/domain/spectral.py
tsextract/domain/statistics.py
tsextract/domain/temporal.py
tsextract/feature_extraction/__init__.py
tsextract/feature_extraction/extract.py
tsextract/feature_extraction/helper.py
tsextract/plots/__init__.py
tsextract/plots/eval.py
tsextract-0.0.9.dist-info/LICENSE
tsextract-0.0.9.dist-info/METADATA
tsextract-0.0.9.dist-info/WHEEL
tsextract-0.0.9.dist-info/top_level.txt
tsextract-0.0.9.dist-info/RECORD
