Metadata-Version: 2.1
Name: tsextract
Version: 0.0.9
Summary: Time series data preprocessing
Home-page: https://github.com/cydal/tsExtract/tree/master/tsextract
Author: Sijuade Oguntayo
Author-email: cydalsij@outlook.com
License: GNU GPL
Platform: UNKNOWN
Classifier: Programming Language :: Python :: 3
Classifier: Programming Language :: Python :: 3.6
Classifier: Programming Language :: Python :: 3.7
Classifier: License :: OSI Approved :: GNU General Public License (GPL)
Classifier: Operating System :: OS Independent
Requires-Python: >=3.6
Requires-Dist: pandas (>=1.0.3)
Requires-Dist: plotnine (>=0.0.6)
Requires-Dist: statsmodels (>=0.10.2)
Requires-Dist: scipy (>=1.4.0)
Requires-Dist: matplotlib (>=3.2.1)
Requires-Dist: numpy (>=1.16.4)
